pgserviceparser/__init__.py
pgserviceparser/exceptions.py
pgserviceparser-2.5.0.dist-info/licenses/LICENSE
pgserviceparser-2.5.0.dist-info/METADATA
pgserviceparser-2.5.0.dist-info/WHEEL
pgserviceparser-2.5.0.dist-info/top_level.txt
pgserviceparser-2.5.0.dist-info/RECORD
