Metadata-Version: 2.4
Name: pgserviceparser
Version: 2.5.0
Summary: A package parsing the PostgreSQL connection service file
Author-email: David Signer <info@opengis.ch>, Julien Moura <julien.moura@oslandia.com>, Germán Carrillo <info@opengis.ch>, Denis Rouzaud <info@opengis.ch>
License: MIT License
Project-URL: homepage, https://opengisch.github.io/pgserviceparser/
Project-URL: repository, https://github.com/opengisch/pgserviceparser
Project-URL: tracker, https://github.com/opengisch/pgserviceparser/issues
Keywords: postgres,service
Classifier: Topic :: Database
Classifier: Intended Audience :: System Administrators
Classifier: Intended Audience :: Information Technology
Classifier: Intended Audience :: Developers
Classifier: Programming Language :: Python :: 3
Requires-Python: >=3.9
License-File: LICENSE
Provides-Extra: dev
Requires-Dist: pre-commit<5,>4; extra == "dev"
Provides-Extra: docs
Requires-Dist: mkdocstrings[python]~=0.25; extra == "docs"
Requires-Dist: mkdocs-material<9.7.0,>=9.5.17; extra == "docs"
Requires-Dist: fancyboxmd~=1.1; extra == "docs"
Dynamic: license-file
